telegram_bot_calendar/__init__.py
telegram_bot_calendar/base.py
telegram_bot_calendar/detailed.py
telegram_bot_calendar/static.py
telegram_bot_calendar/wmonth.py
telegram_bot_calendar/wyear.py
python_telegram_bot_calendar-1.0.5.dist-info/LICENSE.txt
python_telegram_bot_calendar-1.0.5.dist-info/METADATA
python_telegram_bot_calendar-1.0.5.dist-info/WHEEL
python_telegram_bot_calendar-1.0.5.dist-info/top_level.txt
python_telegram_bot_calendar-1.0.5.dist-info/RECORD
