Metadata-Version: 2.1
Name: python-telegram-bot-calendar
Version: 1.0.5
Summary: Python inline calendar for telegram bots
Home-page: https://github.com/artembakhanov/python-telegram-bot-calendar
Author: Artem Bakhanov
Author-email: artembakhanov@gmail.com
License: MIT
Download-URL: https://github.com/artembakhanov/python-telegram-bot-calendar/archive/v_1.0.2.tar.gz
Keywords: calendar,telegram,bot,telegram bot
Platform: UNKNOWN
Classifier: Development Status :: 4 - Beta
Classifier: Intended Audience :: Developers
Classifier: License :: OSI Approved :: MIT License
Classifier: Programming Language :: Python :: 3
Classifier: Programming Language :: Python :: 3.4
Classifier: Programming Language :: Python :: 3.5
Classifier: Programming Language :: Python :: 3.6
Classifier: Programming Language :: Python :: 3.6
Classifier: Programming Language :: Python :: 3.7
Classifier: Programming Language :: Python :: 3.8
Classifier: Programming Language :: Python :: 3.9
Provides-Extra: telethon
